{
    "subject": "Art Making and Exhibiting",
    "version": "2024",
    "theme": {
      "primary": "#1C1C1C",
      "secondary": "#282828",
      "tertiary": "#343434",
      "accent": "#C8C8C8",
      "accentDark": "#A8A8A8",
      "success": "#4caf50",
      "warning": "#ff9800",
      "error": "#f44336",
      "neutral": "#607d8b",
      "text": "#FFFFFF",
      "textMuted": "#A0A0A0"
    },
    "categories": [
      {
        "name": "Exam Technique & Presentation",
        "concepts": [
          {
            "id": "ET001",
            "title": "Remove colour insert in reading time",
            "questions": [
              {
                "text": "You should keep the colour insert attached to your exam booklet throughout the exam.",
                "answer": false,
                "explanation": "Remove the colour insert during reading time. This reduces the risk of accidentally overlooking a question or selecting artworks for the wrong questions.",
                "studyTip": "Reading time task #1: Remove the colour insert. Keep it beside you."
              },
              {
                "text": "Removing the colour insert during reading time helps you match artworks to the correct questions.",
                "answer": true,
                "explanation": "With the insert separate, you can easily reference artworks while reading questions and ensure your responses apply to the correct images.",
                "studyTip": "Insert out, artworks visible, questions clear."
              }
            ]
          },
          {
            "id": "ET002",
            "title": "Use specific evidence from artworks",
            "questions": [
              {
                "text": "Describing the general impression of an artwork is enough to support your answer.",
                "answer": false,
                "explanation": "Use specific evidence from the artwork to justify and consolidate your answer. General impressions without specific visual references earn lower marks.",
                "studyTip": "Point to something specific. 'The blue spirals in the background...' not 'the colours...'"
              },
              {
                "text": "High-scoring responses reference specific features in the artwork to support their discussion.",
                "answer": true,
                "explanation": "Stronger responses regularly reference specific visual evidence—particular colours, shapes, textures, or compositional elements—throughout their answers.",
                "studyTip": "Every claim needs visual proof. Where exactly do you see it?"
              }
            ]
          },
          {
            "id": "ET003",
            "title": "Avoid rote-learned responses",
            "questions": [
              {
                "text": "Memorising standard responses about conservation methods will prepare you for any question.",
                "answer": false,
                "explanation": "Don't rely on pre-prepared responses. Rote-learned answers often don't fit the specific question or artwork. Apply your knowledge to what's actually asked.",
                "studyTip": "Learn principles, not scripts. Apply to each unique question."
              },
              {
                "text": "Structuring answers according to command terms helps you apply knowledge effectively.",
                "answer": true,
                "explanation": "Understanding what 'identify', 'discuss', and 'analyse' require helps you give relevant responses rather than generic memorised content.",
                "studyTip": "Match your response to the command term. Discuss ≠ Identify."
              }
            ]
          },
          {
            "id": "ET004",
            "title": "Practise legible handwriting",
            "questions": [
              {
                "text": "If your ideas are good, assessors will work to decipher difficult handwriting.",
                "answer": false,
                "explanation": "You need to practise handwriting regularly to ensure it's legible. Assessors can't award marks for responses they can't read.",
                "studyTip": "Illegible = invisible. Practise writing under timed conditions."
              },
              {
                "text": "Practising handwriting regularly helps ensure assessors can read your responses.",
                "answer": true,
                "explanation": "Clear, legible handwriting is essential. Take time to form letters properly, even under exam pressure.",
                "studyTip": "Slow down slightly. Readable answers beat rushed scrawl."
              }
            ]
          },
          {
            "id": "ET005",
            "title": "Address all parts of questions",
            "questions": [
              {
                "text": "If you write a strong response to part of a question, you'll still score well overall.",
                "answer": false,
                "explanation": "Questions often have multiple parts. You must consider and engage with ALL parts to earn full marks. Missing a component limits your score.",
                "studyTip": "Count the parts. Answer them all."
              },
              {
                "text": "Reading questions carefully and underlining key instructions ensures you address all requirements.",
                "answer": true,
                "explanation": "Underline command terms and requirements during reading time. Check you've addressed each part before moving on.",
                "studyTip": "Underline. Count. Check off as you write."
              }
            ]
          }
        ]
      },
      {
        "name": "Key Terminology",
        "concepts": [
          {
            "id": "KT001",
            "title": "Art form vs technique",
            "questions": [
              {
                "text": "Techniques like 'stippling' or 'lead pencil' can be identified as art forms.",
                "answer": false,
                "explanation": "An art form is not a technique. Art forms include painting, drawing, printmaking, sculpture, ceramics, photography, etc. Stippling is a technique within drawing.",
                "studyTip": "Art form = the category. Technique = how you make it."
              },
              {
                "text": "Art forms are listed on page 12 of the study design and include painting, sculpture, and printmaking.",
                "answer": true,
                "explanation": "Know the defined art forms. When asked about an art form, identify the correct category (e.g., 'oil painting' or 'coloured pencil drawing'), not a technique.",
                "studyTip": "Check page 12. Is it an art form or a technique?"
              }
            ]
          },
          {
            "id": "KT002",
            "title": "Visual language definition",
            "questions": [
              {
                "text": "Visual language just means the art elements and principles used in an artwork.",
                "answer": false,
                "explanation": "Visual language combines art elements AND principles WITH materials, techniques, and processes to communicate meaning. It's broader than just elements and principles.",
                "studyTip": "Visual language = elements + principles + materials + techniques + processes."
              },
              {
                "text": "Visual language includes how materials, techniques, and processes communicate meaning alongside art elements and principles.",
                "answer": true,
                "explanation": "High-scoring responses discuss all aspects of visual language—not just colour and shape, but how the artist's material choices and techniques contribute to meaning.",
                "studyTip": "Don't stop at colour and line. How do materials and techniques communicate?"
              }
            ]
          },
          {
            "id": "KT003",
            "title": "Conservation method vs technique",
            "questions": [
              {
                "text": "Gloves and glazing are conservation methods.",
                "answer": false,
                "explanation": "Use proper naming conventions. 'Handling' is a conservation method; 'gloves' is a technique within that method. 'Framing with glazing' is more accurate than just 'glazing'.",
                "studyTip": "Method = the approach. Technique = specific tool or action within it."
              },
              {
                "text": "Conservation methods include handling, climate control, lighting control, and framing.",
                "answer": true,
                "explanation": "Methods are broader categories. Within 'handling', you might use nitrile gloves. Within 'climate control', you maintain specific temperature and humidity.",
                "studyTip": "Name the method first, then the specific technique."
              }
            ]
          },
          {
            "id": "KT004",
            "title": "Curatorial vs conservation considerations",
            "questions": [
              {
                "text": "Curatorial considerations and conservation considerations are the same thing.",
                "answer": false,
                "explanation": "They're different. Curatorial considerations involve presentation, placement, thematic connections, and viewer experience. Conservation focuses on protecting the artwork from damage.",
                "studyTip": "Curatorial = how to present. Conservation = how to protect."
              },
              {
                "text": "Distinguishing curatorial considerations from conservation knowledge improves exhibition proposal responses.",
                "answer": true,
                "explanation": "Lower-scoring responses mix these up. Strong responses address both separately: how to present for meaning AND how to protect the materials.",
                "studyTip": "Answer both: What's the viewer experience? What protects the work?"
              }
            ]
          },
          {
            "id": "KT005",
            "title": "Specific material identification",
            "questions": [
              {
                "text": "Referring broadly to 'painting' is specific enough when discussing conservation.",
                "answer": false,
                "explanation": "You must identify specific materials—'oil on canvas' or 'synthetic polymer on board'—not just 'painting'. Different materials have different conservation needs.",
                "studyTip": "Oil paint ≠ acrylic. Canvas ≠ board. Be specific."
              },
              {
                "text": "Identifying specific materials like 'oil on canvas' allows you to discuss relevant conservation methods.",
                "answer": true,
                "explanation": "High-scoring responses name exact materials, then explain how conservation methods apply to those specific properties.",
                "studyTip": "Name the material. Explain its properties. Then discuss conservation."
              }
            ]
          }
        ]
      },
      {
        "name": "Conservation & Care",
        "concepts": [
          {
            "id": "CC001",
            "title": "Explain why methods matter",
            "questions": [
              {
                "text": "Listing conservation methods like '50 lux' and '20°C' demonstrates strong understanding.",
                "answer": false,
                "explanation": "Higher-scoring responses explain WHY methods matter—what happens if you don't use them. State the cause and potential damage, not just the numbers.",
                "studyTip": "Don't just list specs. Explain what goes wrong without them."
              },
              {
                "text": "Explaining the effects of light, humidity, and temperature on specific materials shows deeper understanding.",
                "answer": true,
                "explanation": "Strong responses connect methods to consequences: 'High humidity causes canvas to absorb moisture, leading to warping and mould growth.'",
                "studyTip": "Cause → Effect. Why does this material need this protection?"
              }
            ]
          },
          {
            "id": "CC002",
            "title": "Balance storage, transport, and display",
            "questions": [
              {
                "text": "Focusing mainly on display conservation covers the key requirements.",
                "answer": false,
                "explanation": "Questions often require discussion of conservation during storage, transportation, AND display. Address all three in a balanced way.",
                "studyTip": "Three contexts: storage, transport, display. Cover all asked."
              },
              {
                "text": "Balancing discussion across storage, transportation, and display earns higher marks.",
                "answer": true,
                "explanation": "Each context has different considerations. A work needs different protection when stored flat in a solander box versus hung on a gallery wall.",
                "studyTip": "Different context = different methods. Discuss each specifically."
              }
            ]
          },
          {
            "id": "CC003",
            "title": "Link conservation to artist intention",
            "questions": [
              {
                "text": "Conservation is purely technical and doesn't relate to artist intention.",
                "answer": false,
                "explanation": "Understanding WHY conservation matters includes the artist's intention. Preserving colour integrity or surface texture maintains how the artist intended the work to be experienced.",
                "studyTip": "Conservation protects meaning, not just materials."
              },
              {
                "text": "High-scoring responses connect conservation methods to preserving the artist's intended experience.",
                "answer": true,
                "explanation": "Strong responses show understanding beyond facts—why maintaining colour prevents fading that would alter the emotional impact the artist intended.",
                "studyTip": "Ask: What would the artist lose if this wasn't conserved properly?"
              }
            ]
          },
          {
            "id": "CC004",
            "title": "Apply knowledge to specific artworks",
            "questions": [
              {
                "text": "General conservation knowledge applies equally to all artworks.",
                "answer": false,
                "explanation": "Conservation must be individualised to each artwork's materials, scale, and context. Generic responses that could apply to any work score lower.",
                "studyTip": "What's unique about THIS work? Apply conservation to THAT."
              },
              {
                "text": "Effective conservation discussions reference the specific scale and materials of the artwork being discussed.",
                "answer": true,
                "explanation": "A large-scale sculpture has different handling needs than a small watercolour. Reference the actual artwork's properties in your response.",
                "studyTip": "Size matters. Material matters. Context matters. Be specific."
              }
            ]
          },
          {
            "id": "CC005",
            "title": "Condition reports and documentation",
            "questions": [
              {
                "text": "Condition reports are only needed after an artwork is damaged.",
                "answer": false,
                "explanation": "Condition reports should be completed BEFORE and AFTER transportation to document the artwork's state. This helps identify if damage occurred during transit.",
                "studyTip": "Before AND after. Document to detect changes."
              },
              {
                "text": "Discussing condition reports before and after transportation shows understanding of professional practice.",
                "answer": true,
                "explanation": "High-scoring responses mention documentation as part of the handling process, showing awareness of how galleries actually manage artwork movement.",
                "studyTip": "Report before moving. Report after arrival. Compare."
              }
            ]
          }
        ]
      },
      {
        "name": "Exhibition Proposals",
        "concepts": [
          {
            "id": "EP001",
            "title": "Choose appropriate exhibition spaces",
            "questions": [
              {
                "text": "Any major gallery is an appropriate choice for an exhibition proposal.",
                "answer": false,
                "explanation": "The exhibition space must suit the artworks. Nominating a photography gallery for mostly paintings, or a contemporary art space for historical works, shows poor understanding.",
                "studyTip": "Match the space to the works. CCP = photography. ACCA = contemporary."
              },
              {
                "text": "Selecting an exhibition space that aligns with the art forms and period of the artworks strengthens your proposal.",
                "answer": true,
                "explanation": "Strong responses show knowledge of different gallery types and select spaces appropriate to the proposed exhibition's focus.",
                "studyTip": "Know your galleries. What does each one specialise in?"
              }
            ]
          },
          {
            "id": "EP002",
            "title": "Justify placement decisions",
            "questions": [
              {
                "text": "Describing where each artwork would go is enough for a placement discussion.",
                "answer": false,
                "explanation": "You must justify WHY you're placing works in particular positions. How does placement affect viewer experience? How do works relate to each other?",
                "studyTip": "Don't just say where. Say WHY there."
              },
              {
                "text": "Explaining how placement creates dialogue between artworks and affects viewer experience earns higher marks.",
                "answer": true,
                "explanation": "Strong responses discuss spatial arrangement (linear, salon, grouped), sight lines, and how placement supports the exhibition's thematic purpose.",
                "studyTip": "How does this placement serve the theme and the viewer?"
              }
            ]
          },
          {
            "id": "EP003",
            "title": "Integrate curatorial and conservation",
            "questions": [
              {
                "text": "You can discuss curatorial decisions and conservation separately in an exhibition proposal.",
                "answer": false,
                "explanation": "Lower-scoring responses treat these as separate lists. Strong responses integrate them—showing how conservation needs inform presentation decisions.",
                "studyTip": "Weave them together. How does conservation affect curation?"
              },
              {
                "text": "High-scoring proposals show how conservation considerations are integrated into curatorial decisions.",
                "answer": true,
                "explanation": "For example, discussing why a light-sensitive photograph is placed away from windows, serving both conservation (protection) and curation (intimate viewing).",
                "studyTip": "Every curatorial choice can have a conservation reason. Show the connection."
              }
            ]
          },
          {
            "id": "EP004",
            "title": "Analyse relationships between artworks",
            "questions": [
              {
                "text": "Discussing each artwork separately shows thorough knowledge of the works.",
                "answer": false,
                "explanation": "Lower-scoring responses discuss artworks in isolation. You must analyse the RELATIONSHIPS between works—visual, thematic, or conceptual connections.",
                "studyTip": "Don't list artworks. Show how they connect."
              },
              {
                "text": "Strong proposals analyse visual and thematic relationships between the artworks in the proposed exhibition.",
                "answer": true,
                "explanation": "High-scoring responses identify common themes (like 'home'), visual connections (colour palettes, materials), and how works create dialogue when displayed together.",
                "studyTip": "What do these works say to each other?"
              }
            ]
          },
          {
            "id": "EP005",
            "title": "Title reflects curatorial vision",
            "questions": [
              {
                "text": "An exhibition title is optional and doesn't affect your response.",
                "answer": false,
                "explanation": "Many strong responses title their proposed exhibitions. A well-chosen title demonstrates curatorial thinking and gives your proposal focus.",
                "studyTip": "A title shows curatorial vision. 'The Will of Women' beats 'Three Artworks'."
              },
              {
                "text": "Proposing an exhibition title that connects to thematic relationships demonstrates curatorial understanding.",
                "answer": true,
                "explanation": "High-scoring responses often title their exhibitions and explicitly connect the title to the relationships and themes they've identified.",
                "studyTip": "Title it. Then show how everything connects to that title."
              }
            ]
          }
        ]
      },
      {
        "name": "Describing Artworks",
        "concepts": [
          {
            "id": "DA001",
            "title": "Use descriptive art terminology",
            "questions": [
              {
                "text": "Everyday language is fine if you communicate your observations clearly.",
                "answer": false,
                "explanation": "Use accurate art terminology—specific descriptive language for art elements and principles. 'Warm analogous colours' is better than 'nice orange and red tones'.",
                "studyTip": "Art has a vocabulary. Use it precisely."
              },
              {
                "text": "Using specific art terminology like 'complementary colours' and 'asymmetrical balance' strengthens responses.",
                "answer": true,
                "explanation": "Strong responses use the language of the study design accurately and consistently, showing command of subject-specific vocabulary.",
                "studyTip": "Elements: line, shape, colour, tone, texture. Principles: balance, contrast, repetition..."
              }
            ]
          },
          {
            "id": "DA002",
            "title": "Link elements to effects",
            "questions": [
              {
                "text": "Identifying art elements in an artwork is enough to demonstrate understanding.",
                "answer": false,
                "explanation": "You must describe HOW elements are used and what EFFECT they create. 'The artist uses blue' is weaker than 'Cool blues create a calm, oppressive atmosphere'.",
                "studyTip": "Element + Effect. What does it DO?"
              },
              {
                "text": "High-scoring responses link art elements to the effects they create in the artwork.",
                "answer": true,
                "explanation": "Strong responses connect observations to impact: how repetition creates rhythm, how contrast creates focal points, how colour affects mood.",
                "studyTip": "Don't just spot it. Explain what it achieves."
              }
            ]
          },
          {
            "id": "DA003",
            "title": "Break down processes into steps",
            "questions": [
              {
                "text": "Saying 'the artist painted the canvas' adequately describes the process.",
                "answer": false,
                "explanation": "Break processes into steps, including preparation. Describe building the frame, stretching canvas, applying gesso, underpainting, then final layers.",
                "studyTip": "Step by step. What came first? Then what? Then what?"
              },
              {
                "text": "Describing processes step-by-step, including preparation, demonstrates deeper understanding.",
                "answer": true,
                "explanation": "High-scoring responses show understanding of the full process: 'First gessoed the surface, used underpainting to create a neutral ground, then applied wet-on-wet technique.'",
                "studyTip": "Preparation → Process → Finishing. Show the sequence."
              }
            ]
          },
          {
            "id": "DA004",
            "title": "Connect visual language to meaning",
            "questions": [
              {
                "text": "Describing what you see in an artwork is the same as discussing how visual language communicates meaning.",
                "answer": false,
                "explanation": "Lower-scoring responses describe without interpreting. You must connect visual choices to the meanings and ideas they communicate to audiences.",
                "studyTip": "Description ≠ interpretation. What does it MEAN?"
              },
              {
                "text": "Strong responses connect specific visual language choices to the meanings the artist communicates.",
                "answer": true,
                "explanation": "High-scoring responses explain how material choices, techniques, and compositional decisions work together to communicate personal, cultural, or contemporary ideas.",
                "studyTip": "Visual choice → Meaning communicated. Make the link explicit."
              }
            ]
          }
        ]
      },
      {
        "name": "Comparing Artworks",
        "concepts": [
          {
            "id": "CA001",
            "title": "Maintain consistent comparison",
            "questions": [
              {
                "text": "Writing about one artwork thoroughly, then the other, is an effective comparison structure.",
                "answer": false,
                "explanation": "Many students don't maintain consistent comparisons throughout. You must compare directly—point by point—not describe each work separately.",
                "studyTip": "Compare throughout. Don't split into 'Artwork A' then 'Artwork B' sections."
              },
              {
                "text": "Weaving comparison throughout your response, addressing both works together, produces stronger analysis.",
                "answer": true,
                "explanation": "High-scoring responses compare directly: 'While Work A uses warm tones to create intimacy, Work B employs cool blues for distance.'",
                "studyTip": "Both works in every paragraph. 'Similarly...' 'In contrast...' 'Both...'"
              }
            ]
          },
          {
            "id": "CA002",
            "title": "Compare your own work meaningfully",
            "questions": [
              {
                "text": "Describing your school art show is enough when comparing to your own work.",
                "answer": false,
                "explanation": "When comparing conservation of a viewed artwork to your own, apply professional conservation knowledge to YOUR work. Don't just describe how it was displayed at school.",
                "studyTip": "How SHOULD your work be conserved? Apply the knowledge."
              },
              {
                "text": "Applying conservation knowledge to the presentation of your own artwork shows deeper understanding.",
                "answer": true,
                "explanation": "Strong responses consider how professional conservation methods would apply to their own materials and techniques, not just how the school displayed it.",
                "studyTip": "Your work deserves professional conservation too. What would that look like?"
              }
            ]
          },
          {
            "id": "CA003",
            "title": "Compare relatable works",
            "questions": [
              {
                "text": "Any two artworks can be meaningfully compared for conservation purposes.",
                "answer": false,
                "explanation": "Some responses compared sculptures with paintings and simply stated they were 'different'. Choose works with relatable aspects for meaningful comparison.",
                "studyTip": "Find genuine connections. What can you actually compare?"
              },
              {
                "text": "Choosing artworks with comparable materials or considerations enables more meaningful discussion.",
                "answer": true,
                "explanation": "Strong comparisons identify what's similar AND different between works with some shared ground—similar materials, scale, or exhibition contexts.",
                "studyTip": "Similar enough to compare, different enough to contrast."
              }
            ]
          }
        ]
      }
    ]
  }